[
  {
    "trainNumber": "3950",
    "plannedDepartureTime": "2025-11-10T15:49:00+0100",
    "actualDepartureTime": "2025-11-10T15:49:00+0100",
    "direction": "Enkhuizen",
    "isCancelled": false,
    "loggedAt": "2025-11-10T14:47:21.685Z"
  },
  {
    "trainNumber": "3952",
    "plannedDepartureTime": "2025-11-10T16:19:00+0100",
    "actualDepartureTime": "2025-11-10T16:19:00+0100",
    "direction": "Enkhuizen",
    "isCancelled": false,
    "loggedAt": "2025-11-10T15:07:52.023Z"
  },
  {
    "trainNumber": "3954",
    "plannedDepartureTime": "2025-11-10T16:49:00+0100",
    "actualDepartureTime": "2025-11-10T16:49:00+0100",
    "direction": "Enkhuizen",
    "isCancelled": false,
    "loggedAt": "2025-11-10T15:45:24.159Z"
  },
  {
    "trainNumber": "3754",
    "plannedDepartureTime": "2025-11-10T17:06:00+0100",
    "actualDepartureTime": "2025-11-10T17:06:00+0100",
    "direction": "Enkhuizen",
    "isCancelled": false,
    "loggedAt": "2025-11-10T16:01:11.139Z"
  },
  {
    "trainNumber": "3956",
    "plannedDepartureTime": "2025-11-10T17:19:00+0100",
    "actualDepartureTime": "2025-11-10T17:21:13+0100",
    "direction": "Enkhuizen",
    "isCancelled": false,
    "loggedAt": "2025-11-10T16:01:11.139Z"
  },
  {
    "trainNumber": "3756",
    "plannedDepartureTime": "2025-11-10T17:36:00+0100",
    "actualDepartureTime": "2025-11-10T17:36:00+0100",
    "direction": "Enkhuizen",
    "isCancelled": false,
    "loggedAt": "2025-11-10T16:01:11.139Z"
  },
  {
    "trainNumber": "3958",
    "plannedDepartureTime": "2025-11-10T17:49:00+0100",
    "actualDepartureTime": "2025-11-10T17:49:00+0100",
    "direction": "Enkhuizen",
    "isCancelled": false,
    "loggedAt": "2025-11-10T16:01:11.139Z"
  },
  {
    "trainNumber": "3960",
    "plannedDepartureTime": "2025-11-10T18:19:00+0100",
    "actualDepartureTime": "2025-11-10T18:21:03+0100",
    "direction": "Enkhuizen",
    "isCancelled": false,
    "loggedAt": "2025-11-10T17:17:25.174Z"
  },
  {
    "trainNumber": "3962",
    "plannedDepartureTime": "2025-11-10T18:49:00+0100",
    "actualDepartureTime": "2025-11-10T18:49:00+0100",
    "direction": "Enkhuizen",
    "isCancelled": false,
    "loggedAt": "2025-11-10T17:47:21.071Z"
  },
  {
    "trainNumber": "3964",
    "plannedDepartureTime": "2025-11-10T19:19:00+0100",
    "actualDepartureTime": "2025-11-10T19:19:00+0100",
    "direction": "Enkhuizen",
    "isCancelled": false,
    "loggedAt": "2025-11-10T17:57:21.055Z"
  },
  {
    "trainNumber": "2966",
    "plannedDepartureTime": "2025-11-10T19:51:00+0100",
    "actualDepartureTime": "2025-11-10T19:54:12+0100",
    "direction": "Enkhuizen",
    "isCancelled": false,
    "loggedAt": "2025-11-10T18:47:23.132Z"
  },
  {
    "trainNumber": "2968",
    "plannedDepartureTime": "2025-11-10T20:22:00+0100",
    "actualDepartureTime": "2025-11-10T20:22:00+0100",
    "direction": "Enkhuizen",
    "isCancelled": false,
    "loggedAt": "2025-11-10T19:17:23.063Z"
  },
  {
    "trainNumber": "2970",
    "plannedDepartureTime": "2025-11-10T20:52:00+0100",
    "actualDepartureTime": "2025-11-10T21:01:22+0100",
    "direction": "Enkhuizen",
    "isCancelled": false,
    "loggedAt": "2025-11-10T19:57:29.402Z"
  },
  {
    "trainNumber": "2972",
    "plannedDepartureTime": "2025-11-10T21:22:00+0100",
    "actualDepartureTime": "2025-11-10T21:22:00+0100",
    "direction": "Enkhuizen",
    "isCancelled": false,
    "loggedAt": "2025-11-10T20:17:29.225Z"
  },
  {
    "trainNumber": "2974",
    "plannedDepartureTime": "2025-11-10T21:52:00+0100",
    "actualDepartureTime": "2025-11-10T21:52:00+0100",
    "direction": "Enkhuizen",
    "isCancelled": false,
    "loggedAt": "2025-11-10T20:37:29.273Z"
  },
  {
    "trainNumber": "2976",
    "plannedDepartureTime": "2025-11-10T22:22:00+0100",
    "actualDepartureTime": "2025-11-10T22:27:53+0100",
    "direction": "Enkhuizen",
    "isCancelled": false,
    "loggedAt": "2025-11-10T21:20:26.768Z"
  },
  {
    "trainNumber": "2978",
    "plannedDepartureTime": "2025-11-10T22:52:00+0100",
    "actualDepartureTime": "2025-11-10T22:54:17+0100",
    "direction": "Enkhuizen",
    "isCancelled": false,
    "loggedAt": "2025-11-10T21:38:31.435Z"
  },
  {
    "trainNumber": "2980",
    "plannedDepartureTime": "2025-11-10T23:22:00+0100",
    "actualDepartureTime": "2025-11-10T23:22:00+0100",
    "direction": "Enkhuizen",
    "isCancelled": false,
    "loggedAt": "2025-11-10T21:38:31.435Z"
  },
  {
    "trainNumber": "2982",
    "plannedDepartureTime": "2025-11-10T23:52:00+0100",
    "actualDepartureTime": "2025-11-10T23:52:00+0100",
    "direction": "Enkhuizen",
    "isCancelled": false,
    "loggedAt": "2025-11-10T22:48:16.253Z"
  },
  {
    "trainNumber": "2912",
    "plannedDepartureTime": "2025-11-11T06:22:00+0100",
    "actualDepartureTime": "2025-11-11T06:22:00+0100",
    "direction": "Enkhuizen",
    "isCancelled": false,
    "loggedAt": "2025-11-11T05:17:04.712Z"
  },
  {
    "trainNumber": "2914",
    "plannedDepartureTime": "2025-11-11T06:51:00+0100",
    "actualDepartureTime": "2025-11-11T06:58:38+0100",
    "direction": "Enkhuizen",
    "isCancelled": false,
    "loggedAt": "2025-11-11T05:34:33.637Z"
  },
  {
    "trainNumber": "2916",
    "plannedDepartureTime": "2025-11-11T07:21:00+0100",
    "actualDepartureTime": "2025-11-11T07:21:00+0100",
    "direction": "Enkhuizen",
    "isCancelled": false,
    "loggedAt": "2025-11-11T05:34:33.637Z"
  },
  {
    "trainNumber": "3918",
    "plannedDepartureTime": "2025-11-11T07:49:00+0100",
    "actualDepartureTime": "2025-11-11T07:50:47+0100",
    "direction": "Enkhuizen",
    "isCancelled": false,
    "loggedAt": "2025-11-11T06:42:03.516Z"
  },
  {
    "trainNumber": "3920",
    "plannedDepartureTime": "2025-11-11T08:19:00+0100",
    "actualDepartureTime": "2025-11-11T08:27:17+0100",
    "direction": "Enkhuizen",
    "isCancelled": false,
    "loggedAt": "2025-11-11T06:25:01.521Z"
  },
  {
    "trainNumber": "303920",
    "plannedDepartureTime": "2025-11-11T08:19:00+0100",
    "actualDepartureTime": "2025-11-11T08:19:00+0100",
    "direction": "Enkhuizen",
    "isCancelled": false,
    "loggedAt": "2025-11-11T06:58:42.349Z"
  },
  {
    "trainNumber": "3922",
    "plannedDepartureTime": "2025-11-11T08:49:00+0100",
    "actualDepartureTime": "2025-11-11T08:59:06+0100",
    "direction": "Enkhuizen",
    "isCancelled": false,
    "loggedAt": "2025-11-11T07:51:20.923Z"
  },
  {
    "trainNumber": "3924",
    "plannedDepartureTime": "2025-11-11T09:19:00+0100",
    "actualDepartureTime": "2025-11-11T09:19:00+0100",
    "direction": "Enkhuizen",
    "isCancelled": false,
    "loggedAt": "2025-11-11T07:51:20.923Z"
  },
  {
    "trainNumber": "3926",
    "plannedDepartureTime": "2025-11-11T09:49:00+0100",
    "actualDepartureTime": "2025-11-11T09:50:07+0100",
    "direction": "Enkhuizen",
    "isCancelled": false,
    "loggedAt": "2025-11-11T08:36:34.848Z"
  },
  {
    "trainNumber": "3928",
    "plannedDepartureTime": "2025-11-11T10:19:00+0100",
    "actualDepartureTime": "2025-11-11T10:20:22+0100",
    "direction": "Enkhuizen",
    "isCancelled": false,
    "loggedAt": "2025-11-11T09:16:44.298Z"
  },
  {
    "trainNumber": "3930",
    "plannedDepartureTime": "2025-11-11T10:49:00+0100",
    "actualDepartureTime": "2025-11-11T10:49:00+0100",
    "direction": "Enkhuizen",
    "isCancelled": false,
    "loggedAt": "2025-11-11T09:32:57.958Z"
  },
  {
    "trainNumber": "3932",
    "plannedDepartureTime": "2025-11-11T11:19:00+0100",
    "actualDepartureTime": "2025-11-11T11:19:00+0100",
    "direction": "Enkhuizen",
    "isCancelled": false,
    "loggedAt": "2025-11-11T10:11:16.976Z"
  },
  {
    "trainNumber": "3934",
    "plannedDepartureTime": "2025-11-11T11:49:00+0100",
    "actualDepartureTime": "2025-11-11T11:49:00+0100",
    "direction": "Enkhuizen",
    "isCancelled": false,
    "loggedAt": "2025-11-11T10:38:35.393Z"
  },
  {
    "trainNumber": "3936",
    "plannedDepartureTime": "2025-11-11T12:19:00+0100",
    "actualDepartureTime": "2025-11-11T12:19:00+0100",
    "direction": "Enkhuizen",
    "isCancelled": false,
    "loggedAt": "2025-11-11T10:55:46.279Z"
  },
  {
    "trainNumber": "3938",
    "plannedDepartureTime": "2025-11-11T12:49:00+0100",
    "actualDepartureTime": "2025-11-11T12:49:00+0100",
    "direction": "Enkhuizen",
    "isCancelled": false,
    "loggedAt": "2025-11-11T11:44:55.430Z"
  },
  {
    "trainNumber": "3940",
    "plannedDepartureTime": "2025-11-11T13:19:00+0100",
    "actualDepartureTime": "2025-11-11T13:19:00+0100",
    "direction": "Enkhuizen",
    "isCancelled": false,
    "loggedAt": "2025-11-11T12:06:07.853Z"
  },
  {
    "trainNumber": "3942",
    "plannedDepartureTime": "2025-11-11T13:49:00+0100",
    "actualDepartureTime": "2025-11-11T13:49:00+0100",
    "direction": "Enkhuizen",
    "isCancelled": false,
    "loggedAt": "2025-11-11T12:20:26.645Z"
  },
  {
    "trainNumber": "3944",
    "plannedDepartureTime": "2025-11-11T14:19:00+0100",
    "actualDepartureTime": "2025-11-11T14:19:00+0100",
    "direction": "Enkhuizen",
    "isCancelled": false,
    "loggedAt": "2025-11-11T13:15:39.997Z"
  },
  {
    "trainNumber": "3946",
    "plannedDepartureTime": "2025-11-11T14:49:00+0100",
    "actualDepartureTime": "2025-11-11T14:49:00+0100",
    "direction": "Enkhuizen",
    "isCancelled": false,
    "loggedAt": "2025-11-11T13:48:57.217Z"
  },
  {
    "trainNumber": "3948",
    "plannedDepartureTime": "2025-11-11T15:19:00+0100",
    "actualDepartureTime": "2025-11-11T15:19:00+0100",
    "direction": "Enkhuizen",
    "isCancelled": false,
    "loggedAt": "2025-11-11T13:48:57.217Z"
  },
  {
    "trainNumber": "3952",
    "plannedDepartureTime": "2025-11-11T16:19:00+0100",
    "actualDepartureTime": "2025-11-11T16:21:36+0100",
    "direction": "Enkhuizen",
    "isCancelled": false,
    "loggedAt": "2025-11-11T15:21:08.605Z"
  },
  {
    "trainNumber": "3954",
    "plannedDepartureTime": "2025-11-11T16:49:00+0100",
    "actualDepartureTime": "2025-11-11T16:50:51+0100",
    "direction": "Enkhuizen",
    "isCancelled": false,
    "loggedAt": "2025-11-11T15:49:12.826Z"
  },
  {
    "trainNumber": "3754",
    "plannedDepartureTime": "2025-11-11T17:06:00+0100",
    "actualDepartureTime": "2025-11-11T17:08:00+0100",
    "direction": "Enkhuizen",
    "isCancelled": false,
    "loggedAt": "2025-11-11T16:07:12.780Z"
  },
  {
    "trainNumber": "3956",
    "plannedDepartureTime": "2025-11-11T17:19:00+0100",
    "actualDepartureTime": "2025-11-11T17:19:00+0100",
    "direction": "Enkhuizen",
    "isCancelled": false,
    "loggedAt": "2025-11-11T16:13:12.924Z"
  },
  {
    "trainNumber": "3756",
    "plannedDepartureTime": "2025-11-11T17:36:00+0100",
    "actualDepartureTime": "2025-11-11T17:36:00+0100",
    "direction": "Enkhuizen",
    "isCancelled": false,
    "loggedAt": "2025-11-11T16:34:31.320Z"
  },
  {
    "trainNumber": "3958",
    "plannedDepartureTime": "2025-11-11T17:49:00+0100",
    "actualDepartureTime": "2025-11-11T17:49:00+0100",
    "direction": "Enkhuizen",
    "isCancelled": false,
    "loggedAt": "2025-11-11T16:43:43.161Z"
  },
  {
    "trainNumber": "3960",
    "plannedDepartureTime": "2025-11-11T18:19:00+0100",
    "actualDepartureTime": "2025-11-11T18:19:00+0100",
    "direction": "Enkhuizen",
    "isCancelled": false,
    "loggedAt": "2025-11-11T17:09:22.042Z"
  },
  {
    "trainNumber": "3962",
    "plannedDepartureTime": "2025-11-11T18:49:00+0100",
    "actualDepartureTime": "2025-11-11T18:49:00+0100",
    "direction": "Enkhuizen",
    "isCancelled": false,
    "loggedAt": "2025-11-11T17:42:46.083Z"
  },
  {
    "trainNumber": "3964",
    "plannedDepartureTime": "2025-11-11T19:19:00+0100",
    "actualDepartureTime": "2025-11-11T19:19:00+0100",
    "direction": "Enkhuizen",
    "isCancelled": false,
    "loggedAt": "2025-11-11T18:16:46.461Z"
  },
  {
    "trainNumber": "2966",
    "plannedDepartureTime": "2025-11-11T19:51:00+0100",
    "actualDepartureTime": "2025-11-11T20:03:05+0100",
    "direction": "Enkhuizen",
    "isCancelled": false,
    "loggedAt": "2025-11-11T18:54:46.889Z"
  },
  {
    "trainNumber": "2968",
    "plannedDepartureTime": "2025-11-11T20:22:00+0100",
    "actualDepartureTime": "2025-11-11T20:29:32+0100",
    "direction": "Enkhuizen",
    "isCancelled": false,
    "loggedAt": "2025-11-11T19:27:37.952Z"
  },
  {
    "trainNumber": "2970",
    "plannedDepartureTime": "2025-11-11T20:52:00+0100",
    "actualDepartureTime": "2025-11-11T20:55:26+0100",
    "direction": "Enkhuizen",
    "isCancelled": false,
    "loggedAt": "2025-11-11T19:54:13.668Z"
  },
  {
    "trainNumber": "2972",
    "plannedDepartureTime": "2025-11-11T21:22:00+0100",
    "actualDepartureTime": "2025-11-11T21:26:46+0100",
    "direction": "Enkhuizen",
    "isCancelled": false,
    "loggedAt": "2025-11-11T20:29:27.378Z"
  },
  {
    "trainNumber": "2974",
    "plannedDepartureTime": "2025-11-11T21:52:00+0100",
    "actualDepartureTime": "2025-11-11T21:54:16+0100",
    "direction": "Enkhuizen",
    "isCancelled": false,
    "loggedAt": "2025-11-11T20:53:27.506Z"
  },
  {
    "trainNumber": "2976",
    "plannedDepartureTime": "2025-11-11T22:22:00+0100",
    "actualDepartureTime": "2025-11-11T22:23:38+0100",
    "direction": "Enkhuizen",
    "isCancelled": false,
    "loggedAt": "2025-11-11T21:23:27.611Z"
  },
  {
    "trainNumber": "2978",
    "plannedDepartureTime": "2025-11-11T22:52:00+0100",
    "actualDepartureTime": "2025-11-11T22:52:00+0100",
    "direction": "Enkhuizen",
    "isCancelled": false,
    "loggedAt": "2025-11-11T21:50:27.633Z"
  },
  {
    "trainNumber": "2980",
    "plannedDepartureTime": "2025-11-11T23:22:00+0100",
    "actualDepartureTime": "2025-11-11T23:26:04+0100",
    "direction": "Enkhuizen",
    "isCancelled": false,
    "loggedAt": "2025-11-11T22:23:27.573Z"
  },
  {
    "trainNumber": "2982",
    "plannedDepartureTime": "2025-11-11T23:52:00+0100",
    "actualDepartureTime": "2025-11-11T23:55:16+0100",
    "direction": "Enkhuizen",
    "isCancelled": false,
    "loggedAt": "2025-11-11T22:41:36.629Z"
  },
  {
    "trainNumber": "2912",
    "plannedDepartureTime": "2025-11-12T06:22:00+0100",
    "actualDepartureTime": "2025-11-12T06:22:00+0100",
    "direction": "Enkhuizen",
    "isCancelled": false,
    "loggedAt": "2025-11-12T05:19:25.458Z"
  },
  {
    "trainNumber": "2914",
    "plannedDepartureTime": "2025-11-12T06:51:00+0100",
    "actualDepartureTime": "2025-11-12T06:53:32+0100",
    "direction": "Enkhuizen",
    "isCancelled": false,
    "loggedAt": "2025-11-12T05:50:59.494Z"
  },
  {
    "trainNumber": "2916",
    "plannedDepartureTime": "2025-11-12T07:21:00+0100",
    "actualDepartureTime": "2025-11-12T07:21:00+0100",
    "direction": "Enkhuizen",
    "isCancelled": false,
    "loggedAt": "2025-11-12T06:06:47.597Z"
  },
  {
    "trainNumber": "3918",
    "plannedDepartureTime": "2025-11-12T07:49:00+0100",
    "actualDepartureTime": "2025-11-12T07:49:00+0100",
    "direction": "Enkhuizen",
    "isCancelled": false,
    "loggedAt": "2025-11-12T06:40:16.705Z"
  },
  {
    "trainNumber": "3920",
    "plannedDepartureTime": "2025-11-12T08:19:00+0100",
    "actualDepartureTime": "2025-11-12T08:19:00+0100",
    "direction": "Enkhuizen",
    "isCancelled": false,
    "loggedAt": "2025-11-12T06:40:16.705Z"
  },
  {
    "trainNumber": "3922",
    "plannedDepartureTime": "2025-11-12T08:49:00+0100",
    "actualDepartureTime": "2025-11-12T08:49:00+0100",
    "direction": "Enkhuizen",
    "isCancelled": false,
    "loggedAt": "2025-11-12T07:46:29.809Z"
  },
  {
    "trainNumber": "3924",
    "plannedDepartureTime": "2025-11-12T09:19:00+0100",
    "actualDepartureTime": "2025-11-12T09:19:00+0100",
    "direction": "Enkhuizen",
    "isCancelled": false,
    "loggedAt": "2025-11-12T08:16:29.458Z"
  },
  {
    "trainNumber": "3926",
    "plannedDepartureTime": "2025-11-12T09:49:00+0100",
    "actualDepartureTime": "2025-11-12T09:50:42+0100",
    "direction": "Enkhuizen",
    "isCancelled": false,
    "loggedAt": "2025-11-12T08:49:29.506Z"
  },
  {
    "trainNumber": "3928",
    "plannedDepartureTime": "2025-11-12T10:19:00+0100",
    "actualDepartureTime": "2025-11-12T10:19:00+0100",
    "direction": "Enkhuizen",
    "isCancelled": false,
    "loggedAt": "2025-11-12T09:16:29.522Z"
  },
  {
    "trainNumber": "3930",
    "plannedDepartureTime": "2025-11-12T10:49:00+0100",
    "actualDepartureTime": "2025-11-12T10:49:00+0100",
    "direction": "Enkhuizen",
    "isCancelled": false,
    "loggedAt": "2025-11-12T09:46:29.503Z"
  },
  {
    "trainNumber": "3932",
    "plannedDepartureTime": "2025-11-12T11:19:00+0100",
    "actualDepartureTime": "2025-11-12T11:19:00+0100",
    "direction": "Enkhuizen",
    "isCancelled": false,
    "loggedAt": "2025-11-12T10:16:29.752Z"
  },
  {
    "trainNumber": "3934",
    "plannedDepartureTime": "2025-11-12T11:49:00+0100",
    "actualDepartureTime": "2025-11-12T11:49:00+0100",
    "direction": "Enkhuizen",
    "isCancelled": false,
    "loggedAt": "2025-11-12T10:46:29.736Z"
  },
  {
    "trainNumber": "3936",
    "plannedDepartureTime": "2025-11-12T12:19:00+0100",
    "actualDepartureTime": "2025-11-12T12:23:25+0100",
    "direction": "Enkhuizen",
    "isCancelled": false,
    "loggedAt": "2025-11-12T11:22:29.646Z"
  },
  {
    "trainNumber": "3938",
    "plannedDepartureTime": "2025-11-12T12:49:00+0100",
    "actualDepartureTime": "2025-11-12T12:49:00+0100",
    "direction": "Enkhuizen",
    "isCancelled": false,
    "loggedAt": "2025-11-12T11:46:29.622Z"
  },
  {
    "trainNumber": "3940",
    "plannedDepartureTime": "2025-11-12T13:19:00+0100",
    "actualDepartureTime": "2025-11-12T13:19:00+0100",
    "direction": "Enkhuizen",
    "isCancelled": false,
    "loggedAt": "2025-11-12T12:16:29.606Z"
  },
  {
    "trainNumber": "3942",
    "plannedDepartureTime": "2025-11-12T13:49:00+0100",
    "actualDepartureTime": "2025-11-12T13:49:00+0100",
    "direction": "Enkhuizen",
    "isCancelled": false,
    "loggedAt": "2025-11-12T12:46:29.629Z"
  },
  {
    "trainNumber": "3944",
    "plannedDepartureTime": "2025-11-12T14:19:00+0100",
    "actualDepartureTime": "2025-11-12T14:19:00+0100",
    "direction": "Enkhuizen",
    "isCancelled": false,
    "loggedAt": "2025-11-12T13:16:16.278Z"
  },
  {
    "trainNumber": "3946",
    "plannedDepartureTime": "2025-11-12T14:49:00+0100",
    "actualDepartureTime": "2025-11-12T14:49:00+0100",
    "direction": "Enkhuizen",
    "isCancelled": false,
    "loggedAt": "2025-11-12T13:46:16.484Z"
  },
  {
    "trainNumber": "3948",
    "plannedDepartureTime": "2025-11-12T15:19:00+0100",
    "actualDepartureTime": "2025-11-12T15:37:47+0100",
    "direction": "Enkhuizen",
    "isCancelled": false,
    "loggedAt": "2025-11-12T14:34:16.155Z"
  },
  {
    "trainNumber": "3954",
    "plannedDepartureTime": "2025-11-12T16:49:00+0100",
    "actualDepartureTime": "2025-11-12T16:49:00+0100",
    "direction": "Enkhuizen",
    "isCancelled": false,
    "loggedAt": "2025-11-12T15:46:16.285Z"
  },
  {
    "trainNumber": "3754",
    "plannedDepartureTime": "2025-11-12T17:06:00+0100",
    "actualDepartureTime": "2025-11-12T17:06:00+0100",
    "direction": "Enkhuizen",
    "isCancelled": false,
    "loggedAt": "2025-11-12T16:04:15.961Z"
  },
  {
    "trainNumber": "3956",
    "plannedDepartureTime": "2025-11-12T17:19:00+0100",
    "actualDepartureTime": "2025-11-12T17:19:00+0100",
    "direction": "Enkhuizen",
    "isCancelled": false,
    "loggedAt": "2025-11-12T16:16:16.358Z"
  },
  {
    "trainNumber": "3756",
    "plannedDepartureTime": "2025-11-12T17:36:00+0100",
    "actualDepartureTime": "2025-11-12T17:36:00+0100",
    "direction": "Enkhuizen",
    "isCancelled": false,
    "loggedAt": "2025-11-12T16:25:16.238Z"
  },
  {
    "trainNumber": "3958",
    "plannedDepartureTime": "2025-11-12T17:49:00+0100",
    "actualDepartureTime": "2025-11-12T17:49:00+0100",
    "direction": "Enkhuizen",
    "isCancelled": false,
    "loggedAt": "2025-11-12T16:25:16.238Z"
  },
  {
    "trainNumber": "3962",
    "plannedDepartureTime": "2025-11-12T18:49:00+0100",
    "actualDepartureTime": "2025-11-12T18:49:00+0100",
    "direction": "Enkhuizen",
    "isCancelled": false,
    "loggedAt": "2025-11-12T17:46:01.452Z"
  },
  {
    "trainNumber": "3964",
    "plannedDepartureTime": "2025-11-12T19:19:00+0100",
    "actualDepartureTime": "2025-11-12T19:19:00+0100",
    "direction": "Enkhuizen",
    "isCancelled": false,
    "loggedAt": "2025-11-12T18:19:01.422Z"
  },
  {
    "trainNumber": "2966",
    "plannedDepartureTime": "2025-11-12T19:51:00+0100",
    "actualDepartureTime": "2025-11-12T19:51:00+0100",
    "direction": "Enkhuizen",
    "isCancelled": false,
    "loggedAt": "2025-11-12T18:49:01.334Z"
  },
  {
    "trainNumber": "2968",
    "plannedDepartureTime": "2025-11-12T20:22:00+0100",
    "actualDepartureTime": "2025-11-12T20:23:23+0100",
    "direction": "Enkhuizen",
    "isCancelled": false,
    "loggedAt": "2025-11-12T19:22:01.500Z"
  },
  {
    "trainNumber": "2970",
    "plannedDepartureTime": "2025-11-12T20:52:00+0100",
    "actualDepartureTime": "2025-11-12T20:52:00+0100",
    "direction": "Enkhuizen",
    "isCancelled": false,
    "loggedAt": "2025-11-12T19:40:01.428Z"
  },
  {
    "trainNumber": "2972",
    "plannedDepartureTime": "2025-11-12T21:22:00+0100",
    "actualDepartureTime": "2025-11-12T21:27:09+0100",
    "direction": "Enkhuizen",
    "isCancelled": false,
    "loggedAt": "2025-11-12T20:25:08.613Z"
  },
  {
    "trainNumber": "2974",
    "plannedDepartureTime": "2025-11-12T21:52:00+0100",
    "actualDepartureTime": "2025-11-12T21:52:00+0100",
    "direction": "Enkhuizen",
    "isCancelled": false,
    "loggedAt": "2025-11-12T20:50:10.613Z"
  },
  {
    "trainNumber": "2976",
    "plannedDepartureTime": "2025-11-12T22:22:00+0100",
    "actualDepartureTime": "2025-11-12T22:22:00+0100",
    "direction": "Enkhuizen",
    "isCancelled": false,
    "loggedAt": "2025-11-12T21:06:26.923Z"
  },
  {
    "trainNumber": "2978",
    "plannedDepartureTime": "2025-11-12T22:52:00+0100",
    "actualDepartureTime": "2025-11-12T22:52:00+0100",
    "direction": "Enkhuizen",
    "isCancelled": false,
    "loggedAt": "2025-11-12T21:33:41.263Z"
  },
  {
    "trainNumber": "2980",
    "plannedDepartureTime": "2025-11-12T23:22:00+0100",
    "actualDepartureTime": "2025-11-12T23:24:51+0100",
    "direction": "Enkhuizen",
    "isCancelled": false,
    "loggedAt": "2025-11-12T22:23:49.068Z"
  },
  {
    "trainNumber": "2912",
    "plannedDepartureTime": "2025-11-13T06:22:00+0100",
    "actualDepartureTime": "2025-11-13T06:22:00+0100",
    "direction": "Enkhuizen",
    "isCancelled": false,
    "loggedAt": "2025-11-13T05:12:55.609Z"
  },
  {
    "trainNumber": "2914",
    "plannedDepartureTime": "2025-11-13T06:51:00+0100",
    "actualDepartureTime": "2025-11-13T06:51:00+0100",
    "direction": "Enkhuizen",
    "isCancelled": false,
    "loggedAt": "2025-11-13T05:46:10.978Z"
  },
  {
    "trainNumber": "2916",
    "plannedDepartureTime": "2025-11-13T07:21:00+0100",
    "actualDepartureTime": "2025-11-13T07:27:52+0100",
    "direction": "Enkhuizen",
    "isCancelled": false,
    "loggedAt": "2025-11-13T06:26:36.207Z"
  },
  {
    "trainNumber": "303926",
    "plannedDepartureTime": "2025-11-13T09:49:00+0100",
    "actualDepartureTime": "2025-11-13T09:49:00+0100",
    "direction": "Enkhuizen",
    "isCancelled": false,
    "loggedAt": "2025-11-13T08:11:07.443Z"
  },
  {
    "trainNumber": "303930",
    "plannedDepartureTime": "2025-11-13T10:49:00+0100",
    "actualDepartureTime": "2025-11-13T10:49:00+0100",
    "direction": "Enkhuizen",
    "isCancelled": false,
    "loggedAt": "2025-11-13T09:46:31.784Z"
  },
  {
    "trainNumber": "3934",
    "plannedDepartureTime": "2025-11-13T11:49:00+0100",
    "actualDepartureTime": "2025-11-13T11:49:00+0100",
    "direction": "Enkhuizen",
    "isCancelled": false,
    "loggedAt": "2025-11-13T10:46:31.872Z"
  },
  {
    "trainNumber": "3936",
    "plannedDepartureTime": "2025-11-13T12:19:00+0100",
    "actualDepartureTime": "2025-11-13T12:38:14+0100",
    "direction": "Enkhuizen",
    "isCancelled": false,
    "loggedAt": "2025-11-13T11:16:31.836Z"
  },
  {
    "trainNumber": "3938",
    "plannedDepartureTime": "2025-11-13T12:49:00+0100",
    "actualDepartureTime": "2025-11-13T12:49:00+0100",
    "direction": "Enkhuizen",
    "isCancelled": false,
    "loggedAt": "2025-11-13T11:23:52.067Z"
  },
  {
    "trainNumber": "3940",
    "plannedDepartureTime": "2025-11-13T13:19:00+0100",
    "actualDepartureTime": "2025-11-13T13:22:32+0100",
    "direction": "Enkhuizen",
    "isCancelled": false,
    "loggedAt": "2025-11-13T12:18:59.559Z"
  },
  {
    "trainNumber": "3942",
    "plannedDepartureTime": "2025-11-13T13:49:00+0100",
    "actualDepartureTime": "2025-11-13T13:49:00+0100",
    "direction": "Enkhuizen",
    "isCancelled": false,
    "loggedAt": "2025-11-13T12:25:48.295Z"
  },
  {
    "trainNumber": "3944",
    "plannedDepartureTime": "2025-11-13T14:19:00+0100",
    "actualDepartureTime": "2025-11-13T14:19:00+0100",
    "direction": "Enkhuizen",
    "isCancelled": false,
    "loggedAt": "2025-11-13T12:25:48.295Z"
  },
  {
    "trainNumber": "3946",
    "plannedDepartureTime": "2025-11-13T14:49:00+0100",
    "actualDepartureTime": "2025-11-13T14:50:25+0100",
    "direction": "Enkhuizen",
    "isCancelled": false,
    "loggedAt": "2025-11-13T13:46:39.628Z"
  },
  {
    "trainNumber": "3948",
    "plannedDepartureTime": "2025-11-13T15:19:00+0100",
    "actualDepartureTime": "2025-11-13T15:19:00+0100",
    "direction": "Enkhuizen",
    "isCancelled": false,
    "loggedAt": "2025-11-13T14:04:04.124Z"
  },
  {
    "trainNumber": "3950",
    "plannedDepartureTime": "2025-11-13T15:49:00+0100",
    "actualDepartureTime": "2025-11-13T15:49:00+0100",
    "direction": "Enkhuizen",
    "isCancelled": false,
    "loggedAt": "2025-11-13T14:36:26.837Z"
  },
  {
    "trainNumber": "3952",
    "plannedDepartureTime": "2025-11-13T16:19:00+0100",
    "actualDepartureTime": "2025-11-13T16:19:00+0100",
    "direction": "Enkhuizen",
    "isCancelled": false,
    "loggedAt": "2025-11-13T15:16:46.493Z"
  },
  {
    "trainNumber": "3954",
    "plannedDepartureTime": "2025-11-13T16:49:00+0100",
    "actualDepartureTime": "2025-11-13T16:59:42+0100",
    "direction": "Enkhuizen",
    "isCancelled": false,
    "loggedAt": "2025-11-13T15:58:46.748Z"
  },
  {
    "trainNumber": "3754",
    "plannedDepartureTime": "2025-11-13T17:06:00+0100",
    "actualDepartureTime": "2025-11-13T17:06:00+0100",
    "direction": "Enkhuizen",
    "isCancelled": false,
    "loggedAt": "2025-11-13T16:04:46.648Z"
  },
  {
    "trainNumber": "3956",
    "plannedDepartureTime": "2025-11-13T17:19:00+0100",
    "actualDepartureTime": "2025-11-13T17:21:12+0100",
    "direction": "Enkhuizen",
    "isCancelled": false,
    "loggedAt": "2025-11-13T16:16:46.519Z"
  },
  {
    "trainNumber": "3756",
    "plannedDepartureTime": "2025-11-13T17:36:00+0100",
    "actualDepartureTime": "2025-11-13T17:36:00+0100",
    "direction": "Enkhuizen",
    "isCancelled": false,
    "loggedAt": "2025-11-13T16:34:30.537Z"
  },
  {
    "trainNumber": "303958",
    "plannedDepartureTime": "2025-11-13T17:49:00+0100",
    "actualDepartureTime": "2025-11-13T17:49:00+0100",
    "direction": "Enkhuizen",
    "isCancelled": false,
    "loggedAt": "2025-11-13T16:34:30.537Z"
  },
  {
    "trainNumber": "3960",
    "plannedDepartureTime": "2025-11-13T18:19:00+0100",
    "actualDepartureTime": "2025-11-13T18:21:29+0100",
    "direction": "Enkhuizen",
    "isCancelled": false,
    "loggedAt": "2025-11-13T17:08:37.351Z"
  },
  {
    "trainNumber": "3962",
    "plannedDepartureTime": "2025-11-13T18:49:00+0100",
    "actualDepartureTime": "2025-11-13T18:56:25+0100",
    "direction": "Enkhuizen",
    "isCancelled": false,
    "loggedAt": "2025-11-13T17:42:24.424Z"
  },
  {
    "trainNumber": "3964",
    "plannedDepartureTime": "2025-11-13T19:19:00+0100",
    "actualDepartureTime": "2025-11-13T19:20:15+0100",
    "direction": "Enkhuizen",
    "isCancelled": false,
    "loggedAt": "2025-11-13T18:16:38.437Z"
  },
  {
    "trainNumber": "2966",
    "plannedDepartureTime": "2025-11-13T19:51:00+0100",
    "actualDepartureTime": "2025-11-13T20:02:11+0100",
    "direction": "Enkhuizen",
    "isCancelled": false,
    "loggedAt": "2025-11-13T18:52:23.381Z"
  },
  {
    "trainNumber": "2968",
    "plannedDepartureTime": "2025-11-13T20:22:00+0100",
    "actualDepartureTime": "2025-11-13T20:34:24+0100",
    "direction": "Enkhuizen",
    "isCancelled": false,
    "loggedAt": "2025-11-13T19:20:30.133Z"
  },
  {
    "trainNumber": "2970",
    "plannedDepartureTime": "2025-11-13T20:52:00+0100",
    "actualDepartureTime": "2025-11-13T21:01:17+0100",
    "direction": "Enkhuizen",
    "isCancelled": false,
    "loggedAt": "2025-11-13T19:53:39.232Z"
  },
  {
    "trainNumber": "2972",
    "plannedDepartureTime": "2025-11-13T21:22:00+0100",
    "actualDepartureTime": "2025-11-13T21:22:00+0100",
    "direction": "Enkhuizen",
    "isCancelled": false,
    "loggedAt": "2025-11-13T20:21:30.206Z"
  },
  {
    "trainNumber": "2974",
    "plannedDepartureTime": "2025-11-13T21:52:00+0100",
    "actualDepartureTime": "2025-11-13T21:52:00+0100",
    "direction": "Enkhuizen",
    "isCancelled": false,
    "loggedAt": "2025-11-13T20:36:40.356Z"
  },
  {
    "trainNumber": "2976",
    "plannedDepartureTime": "2025-11-13T22:22:00+0100",
    "actualDepartureTime": "2025-11-13T22:22:00+0100",
    "direction": "Enkhuizen",
    "isCancelled": false,
    "loggedAt": "2025-11-13T21:21:34.812Z"
  },
  {
    "trainNumber": "2978",
    "plannedDepartureTime": "2025-11-13T22:52:00+0100",
    "actualDepartureTime": "2025-11-13T23:06:37+0100",
    "direction": "Enkhuizen",
    "isCancelled": false,
    "loggedAt": "2025-11-13T22:00:34.852Z"
  },
  {
    "trainNumber": "2980",
    "plannedDepartureTime": "2025-11-13T23:22:00+0100",
    "actualDepartureTime": "2025-11-13T23:23:09+0100",
    "direction": "Enkhuizen",
    "isCancelled": false,
    "loggedAt": "2025-11-13T22:00:34.852Z"
  },
  {
    "trainNumber": "2956",
    "plannedDepartureTime": "2025-11-15T17:21:00+0100",
    "actualDepartureTime": "2025-11-15T17:21:00+0100",
    "direction": "Enkhuizen",
    "isCancelled": false,
    "loggedAt": "2025-11-15T16:19:21.269Z"
  },
  {
    "trainNumber": "2958",
    "plannedDepartureTime": "2025-11-15T17:53:00+0100",
    "actualDepartureTime": "2025-11-15T17:53:00+0100",
    "direction": "Enkhuizen",
    "isCancelled": false,
    "loggedAt": "2025-11-15T16:50:08.181Z"
  },
  {
    "trainNumber": "2960",
    "plannedDepartureTime": "2025-11-15T18:21:00+0100",
    "actualDepartureTime": "2025-11-15T18:21:00+0100",
    "direction": "Enkhuizen",
    "isCancelled": false,
    "loggedAt": "2025-11-15T17:19:54.029Z"
  },
  {
    "trainNumber": "2962",
    "plannedDepartureTime": "2025-11-15T18:52:00+0100",
    "actualDepartureTime": "2025-11-15T18:52:00+0100",
    "direction": "Enkhuizen",
    "isCancelled": false,
    "loggedAt": "2025-11-15T17:49:54.025Z"
  },
  {
    "trainNumber": "2964",
    "plannedDepartureTime": "2025-11-15T19:23:00+0100",
    "actualDepartureTime": "2025-11-15T19:23:00+0100",
    "direction": "Enkhuizen",
    "isCancelled": false,
    "loggedAt": "2025-11-15T18:22:54.190Z"
  },
  {
    "trainNumber": "2966",
    "plannedDepartureTime": "2025-11-15T19:52:00+0100",
    "actualDepartureTime": "2025-11-15T19:52:00+0100",
    "direction": "Enkhuizen",
    "isCancelled": false,
    "loggedAt": "2025-11-15T18:49:54.070Z"
  },
  {
    "trainNumber": "2968",
    "plannedDepartureTime": "2025-11-15T20:22:00+0100",
    "actualDepartureTime": "2025-11-15T20:22:00+0100",
    "direction": "Enkhuizen",
    "isCancelled": false,
    "loggedAt": "2025-11-15T19:19:54.101Z"
  },
  {
    "trainNumber": "2970",
    "plannedDepartureTime": "2025-11-15T20:51:00+0100",
    "actualDepartureTime": "2025-11-15T20:51:00+0100",
    "direction": "Enkhuizen",
    "isCancelled": false,
    "loggedAt": "2025-11-15T19:49:54.251Z"
  },
  {
    "trainNumber": "2972",
    "plannedDepartureTime": "2025-11-15T21:22:00+0100",
    "actualDepartureTime": "2025-11-15T21:22:00+0100",
    "direction": "Enkhuizen",
    "isCancelled": false,
    "loggedAt": "2025-11-15T20:20:15.320Z"
  },
  {
    "trainNumber": "2974",
    "plannedDepartureTime": "2025-11-15T21:52:00+0100",
    "actualDepartureTime": "2025-11-15T21:52:00+0100",
    "direction": "Enkhuizen",
    "isCancelled": false,
    "loggedAt": "2025-11-15T20:47:15.440Z"
  },
  {
    "trainNumber": "2976",
    "plannedDepartureTime": "2025-11-15T22:22:00+0100",
    "actualDepartureTime": "2025-11-15T22:25:18+0100",
    "direction": "Enkhuizen",
    "isCancelled": false,
    "loggedAt": "2025-11-15T21:22:58.891Z"
  },
  {
    "trainNumber": "2978",
    "plannedDepartureTime": "2025-11-15T22:52:00+0100",
    "actualDepartureTime": "2025-11-15T22:53:03+0100",
    "direction": "Enkhuizen",
    "isCancelled": false,
    "loggedAt": "2025-11-15T21:44:13.917Z"
  },
  {
    "trainNumber": "2980",
    "plannedDepartureTime": "2025-11-15T23:22:00+0100",
    "actualDepartureTime": "2025-11-15T23:28:44+0100",
    "direction": "Enkhuizen",
    "isCancelled": false,
    "loggedAt": "2025-11-15T22:26:37.474Z"
  },
  {
    "trainNumber": "2982",
    "plannedDepartureTime": "2025-11-15T23:52:00+0100",
    "actualDepartureTime": "2025-11-15T23:52:00+0100",
    "direction": "Enkhuizen",
    "isCancelled": false,
    "loggedAt": "2025-11-15T22:44:30.573Z"
  },
  {
    "trainNumber": "2984",
    "plannedDepartureTime": "2025-11-16T00:22:00+0100",
    "actualDepartureTime": "2025-11-16T00:22:00+0100",
    "direction": "Enkhuizen",
    "isCancelled": false,
    "loggedAt": "2025-11-15T23:04:18.458Z"
  },
  {
    "trainNumber": "202986",
    "plannedDepartureTime": "2025-11-16T00:52:00+0100",
    "actualDepartureTime": "2025-11-16T00:52:00+0100",
    "direction": "Enkhuizen",
    "isCancelled": false,
    "loggedAt": "2025-11-15T23:46:15.483Z"
  },
  {
    "trainNumber": "2990",
    "plannedDepartureTime": "2025-11-16T01:52:00+0100",
    "actualDepartureTime": "2025-11-16T01:52:00+0100",
    "direction": "Enkhuizen",
    "isCancelled": false,
    "loggedAt": "2025-11-16T00:47:03.706Z"
  },
  {
    "trainNumber": "2916",
    "plannedDepartureTime": "2025-11-16T07:22:00+0100",
    "actualDepartureTime": "2025-11-16T07:22:00+0100",
    "direction": "Enkhuizen",
    "isCancelled": false,
    "loggedAt": "2025-11-16T06:20:02.427Z"
  },
  {
    "trainNumber": "2920",
    "plannedDepartureTime": "2025-11-16T08:22:00+0100",
    "actualDepartureTime": "2025-11-16T08:22:00+0100",
    "direction": "Enkhuizen",
    "isCancelled": false,
    "loggedAt": "2025-11-16T07:11:00.881Z"
  },
  {
    "trainNumber": "2922",
    "plannedDepartureTime": "2025-11-16T08:52:00+0100",
    "actualDepartureTime": "2025-11-16T08:52:00+0100",
    "direction": "Enkhuizen",
    "isCancelled": false,
    "loggedAt": "2025-11-16T07:46:54.367Z"
  },
  {
    "trainNumber": "2924",
    "plannedDepartureTime": "2025-11-16T09:22:00+0100",
    "actualDepartureTime": "2025-11-16T09:22:00+0100",
    "direction": "Enkhuizen",
    "isCancelled": false,
    "loggedAt": "2025-11-16T08:02:11.280Z"
  },
  {
    "trainNumber": "2926",
    "plannedDepartureTime": "2025-11-16T09:52:00+0100",
    "actualDepartureTime": "2025-11-16T09:53:24+0100",
    "direction": "Enkhuizen",
    "isCancelled": false,
    "loggedAt": "2025-11-16T08:46:10.265Z"
  },
  {
    "trainNumber": "2928",
    "plannedDepartureTime": "2025-11-16T10:22:00+0100",
    "actualDepartureTime": "2025-11-16T10:22:00+0100",
    "direction": "Enkhuizen",
    "isCancelled": false,
    "loggedAt": "2025-11-16T09:02:20.694Z"
  },
  {
    "trainNumber": "2930",
    "plannedDepartureTime": "2025-11-16T10:51:00+0100",
    "actualDepartureTime": "2025-11-16T10:51:00+0100",
    "direction": "Enkhuizen",
    "isCancelled": false,
    "loggedAt": "2025-11-16T09:02:20.694Z"
  },
  {
    "trainNumber": "2932",
    "plannedDepartureTime": "2025-11-16T11:22:00+0100",
    "actualDepartureTime": "2025-11-16T11:22:00+0100",
    "direction": "Enkhuizen",
    "isCancelled": false,
    "loggedAt": "2025-11-16T10:20:51.739Z"
  },
  {
    "trainNumber": "2934",
    "plannedDepartureTime": "2025-11-16T11:52:00+0100",
    "actualDepartureTime": "2025-11-16T11:52:00+0100",
    "direction": "Enkhuizen",
    "isCancelled": false,
    "loggedAt": "2025-11-16T10:48:59.616Z"
  },
  {
    "trainNumber": "2936",
    "plannedDepartureTime": "2025-11-16T12:22:00+0100",
    "actualDepartureTime": "2025-11-16T12:22:00+0100",
    "direction": "Enkhuizen",
    "isCancelled": false,
    "loggedAt": "2025-11-16T11:06:31.964Z"
  },
  {
    "trainNumber": "2938",
    "plannedDepartureTime": "2025-11-16T12:52:00+0100",
    "actualDepartureTime": "2025-11-16T12:52:00+0100",
    "direction": "Enkhuizen",
    "isCancelled": false,
    "loggedAt": "2025-11-16T11:50:49.469Z"
  },
  {
    "trainNumber": "2940",
    "plannedDepartureTime": "2025-11-16T13:22:00+0100",
    "actualDepartureTime": "2025-11-16T13:22:00+0100",
    "direction": "Enkhuizen",
    "isCancelled": false,
    "loggedAt": "2025-11-16T12:21:26.973Z"
  },
  {
    "trainNumber": "2942",
    "plannedDepartureTime": "2025-11-16T13:52:00+0100",
    "actualDepartureTime": "2025-11-16T13:52:00+0100",
    "direction": "Enkhuizen",
    "isCancelled": false,
    "loggedAt": "2025-11-16T12:51:26.890Z"
  },
  {
    "trainNumber": "2944",
    "plannedDepartureTime": "2025-11-16T14:22:00+0100",
    "actualDepartureTime": "2025-11-16T14:22:00+0100",
    "direction": "Enkhuizen",
    "isCancelled": false,
    "loggedAt": "2025-11-16T13:15:26.960Z"
  },
  {
    "trainNumber": "2946",
    "plannedDepartureTime": "2025-11-16T14:52:00+0100",
    "actualDepartureTime": "2025-11-16T14:52:00+0100",
    "direction": "Enkhuizen",
    "isCancelled": false,
    "loggedAt": "2025-11-16T13:49:42.339Z"
  },
  {
    "trainNumber": "2948",
    "plannedDepartureTime": "2025-11-16T15:22:00+0100",
    "actualDepartureTime": "2025-11-16T15:22:00+0100",
    "direction": "Enkhuizen",
    "isCancelled": false,
    "loggedAt": "2025-11-16T14:07:42.421Z"
  },
  {
    "trainNumber": "2950",
    "plannedDepartureTime": "2025-11-16T15:52:00+0100",
    "actualDepartureTime": "2025-11-16T15:55:26+0100",
    "direction": "Enkhuizen",
    "isCancelled": false,
    "loggedAt": "2025-11-16T14:54:26.461Z"
  },
  {
    "trainNumber": "2952",
    "plannedDepartureTime": "2025-11-16T16:22:00+0100",
    "actualDepartureTime": "2025-11-16T16:22:00+0100",
    "direction": "Enkhuizen",
    "isCancelled": false,
    "loggedAt": "2025-11-16T15:19:03.660Z"
  },
  {
    "trainNumber": "2954",
    "plannedDepartureTime": "2025-11-16T16:52:00+0100",
    "actualDepartureTime": "2025-11-16T16:52:00+0100",
    "direction": "Enkhuizen",
    "isCancelled": false,
    "loggedAt": "2025-11-16T15:46:03.620Z"
  },
  {
    "trainNumber": "2956",
    "plannedDepartureTime": "2025-11-16T17:22:00+0100",
    "actualDepartureTime": "2025-11-16T17:22:00+0100",
    "direction": "Enkhuizen",
    "isCancelled": false,
    "loggedAt": "2025-11-16T16:20:14.704Z"
  },
  {
    "trainNumber": "2958",
    "plannedDepartureTime": "2025-11-16T17:53:00+0100",
    "actualDepartureTime": "2025-11-16T17:53:00+0100",
    "direction": "Enkhuizen",
    "isCancelled": false,
    "loggedAt": "2025-11-16T16:50:15.066Z"
  },
  {
    "trainNumber": "2960",
    "plannedDepartureTime": "2025-11-16T18:22:00+0100",
    "actualDepartureTime": "2025-11-16T18:22:00+0100",
    "direction": "Enkhuizen",
    "isCancelled": false,
    "loggedAt": "2025-11-16T17:20:14.731Z"
  },
  {
    "trainNumber": "2962",
    "plannedDepartureTime": "2025-11-16T18:52:00+0100",
    "actualDepartureTime": "2025-11-16T18:52:00+0100",
    "direction": "Enkhuizen",
    "isCancelled": false,
    "loggedAt": "2025-11-16T17:43:07.138Z"
  },
  {
    "trainNumber": "2964",
    "plannedDepartureTime": "2025-11-16T19:23:00+0100",
    "actualDepartureTime": "2025-11-16T19:23:00+0100",
    "direction": "Enkhuizen",
    "isCancelled": false,
    "loggedAt": "2025-11-16T18:17:47.219Z"
  },
  {
    "trainNumber": "2966",
    "plannedDepartureTime": "2025-11-16T19:52:00+0100",
    "actualDepartureTime": "2025-11-16T19:52:00+0100",
    "direction": "Enkhuizen",
    "isCancelled": false,
    "loggedAt": "2025-11-16T18:49:56.083Z"
  },
  {
    "trainNumber": "2968",
    "plannedDepartureTime": "2025-11-16T20:22:00+0100",
    "actualDepartureTime": "2025-11-16T20:22:00+0100",
    "direction": "Enkhuizen",
    "isCancelled": false,
    "loggedAt": "2025-11-16T19:19:45.872Z"
  },
  {
    "trainNumber": "2970",
    "plannedDepartureTime": "2025-11-16T20:52:00+0100",
    "actualDepartureTime": "2025-11-16T20:52:00+0100",
    "direction": "Enkhuizen",
    "isCancelled": false,
    "loggedAt": "2025-11-16T19:44:44.406Z"
  },
  {
    "trainNumber": "2972",
    "plannedDepartureTime": "2025-11-16T21:22:00+0100",
    "actualDepartureTime": "2025-11-16T21:22:00+0100",
    "direction": "Enkhuizen",
    "isCancelled": false,
    "loggedAt": "2025-11-16T20:21:38.185Z"
  },
  {
    "trainNumber": "2974",
    "plannedDepartureTime": "2025-11-16T21:52:00+0100",
    "actualDepartureTime": "2025-11-16T21:52:00+0100",
    "direction": "Enkhuizen",
    "isCancelled": false,
    "loggedAt": "2025-11-16T20:51:37.863Z"
  },
  {
    "trainNumber": "2976",
    "plannedDepartureTime": "2025-11-16T22:22:00+0100",
    "actualDepartureTime": "2025-11-16T22:22:00+0100",
    "direction": "Enkhuizen",
    "isCancelled": false,
    "loggedAt": "2025-11-16T21:21:35.876Z"
  },
  {
    "trainNumber": "2978",
    "plannedDepartureTime": "2025-11-16T22:52:00+0100",
    "actualDepartureTime": "2025-11-16T22:52:00+0100",
    "direction": "Enkhuizen",
    "isCancelled": false,
    "loggedAt": "2025-11-16T21:44:59.337Z"
  },
  {
    "trainNumber": "2980",
    "plannedDepartureTime": "2025-11-16T23:22:00+0100",
    "actualDepartureTime": "2025-11-16T23:22:00+0100",
    "direction": "Enkhuizen",
    "isCancelled": false,
    "loggedAt": "2025-11-16T22:02:56.068Z"
  },
  {
    "trainNumber": "2982",
    "plannedDepartureTime": "2025-11-16T23:52:00+0100",
    "actualDepartureTime": "2025-11-16T23:52:00+0100",
    "direction": "Enkhuizen",
    "isCancelled": false,
    "loggedAt": "2025-11-16T22:37:43.133Z"
  },
  {
    "trainNumber": "2912",
    "plannedDepartureTime": "2025-11-17T06:22:00+0100",
    "actualDepartureTime": "2025-11-17T06:22:00+0100",
    "direction": "Enkhuizen",
    "isCancelled": false,
    "loggedAt": "2025-11-17T05:20:53.025Z"
  },
  {
    "trainNumber": "2914",
    "plannedDepartureTime": "2025-11-17T06:51:00+0100",
    "actualDepartureTime": "2025-11-17T06:53:04+0100",
    "direction": "Enkhuizen",
    "isCancelled": false,
    "loggedAt": "2025-11-17T05:50:52.733Z"
  },
  {
    "trainNumber": "2916",
    "plannedDepartureTime": "2025-11-17T07:21:00+0100",
    "actualDepartureTime": "2025-11-17T07:21:00+0100",
    "direction": "Enkhuizen",
    "isCancelled": false,
    "loggedAt": "2025-11-17T06:20:52.733Z"
  },
  {
    "trainNumber": "3918",
    "plannedDepartureTime": "2025-11-17T07:49:00+0100",
    "actualDepartureTime": "2025-11-17T07:50:39+0100",
    "direction": "Enkhuizen",
    "isCancelled": false,
    "loggedAt": "2025-11-17T06:41:19.504Z"
  },
  {
    "trainNumber": "3920",
    "plannedDepartureTime": "2025-11-17T08:19:00+0100",
    "actualDepartureTime": "2025-11-17T08:19:00+0100",
    "direction": "Enkhuizen",
    "isCancelled": false,
    "loggedAt": "2025-11-17T06:41:19.504Z"
  },
  {
    "trainNumber": "3922",
    "plannedDepartureTime": "2025-11-17T08:49:00+0100",
    "actualDepartureTime": "2025-11-17T08:49:00+0100",
    "direction": "Enkhuizen",
    "isCancelled": false,
    "loggedAt": "2025-11-17T07:41:08.992Z"
  },
  {
    "trainNumber": "3924",
    "plannedDepartureTime": "2025-11-17T09:19:00+0100",
    "actualDepartureTime": "2025-11-17T09:19:00+0100",
    "direction": "Enkhuizen",
    "isCancelled": false,
    "loggedAt": "2025-11-17T08:17:32.459Z"
  },
  {
    "trainNumber": "3926",
    "plannedDepartureTime": "2025-11-17T09:49:00+0100",
    "actualDepartureTime": "2025-11-17T09:52:58+0100",
    "direction": "Enkhuizen",
    "isCancelled": false,
    "loggedAt": "2025-11-17T08:52:35.467Z"
  },
  {
    "trainNumber": "3928",
    "plannedDepartureTime": "2025-11-17T10:19:00+0100",
    "actualDepartureTime": "2025-11-17T10:19:00+0100",
    "direction": "Enkhuizen",
    "isCancelled": false,
    "loggedAt": "2025-11-17T08:55:35.438Z"
  },
  {
    "trainNumber": "3930",
    "plannedDepartureTime": "2025-11-17T10:49:00+0100",
    "actualDepartureTime": "2025-11-17T10:49:00+0100",
    "direction": "Enkhuizen",
    "isCancelled": false,
    "loggedAt": "2025-11-17T08:55:35.438Z"
  }
]